README.rst
setup.py
suds_requests.py
suds_requests.egg-info/PKG-INFO
suds_requests.egg-info/SOURCES.txt
suds_requests.egg-info/dependency_links.txt
suds_requests.egg-info/requires.txt
suds_requests.egg-info/top_level.txt