Metadata-Version: 1.0
Name: suds-requests
Version: 0.1
Summary: suds_requests
